controlhub/__init__.py
controlhub/config.py
controlhub/desktop.py
controlhub/json_storage.py
controlhub/keyboard.py
controlhub/models.py
controlhub/pocketbase.py
controlhub/search.py
controlhub/web.py
controlhub-0.6.1.dist-info/METADATA
controlhub-0.6.1.dist-info/WHEEL
controlhub-0.6.1.dist-info/licenses/LICENSE
controlhub-0.6.1.dist-info/RECORD
