Metadata-Version: 2.4
Name: controlhub
Version: 0.6.1
Summary: Collection of functions to control a Windows or Linux pc.
Project-URL: Homepage, https://github.com/control-hub/python-package
Project-URL: Issues, https://github.com/control-hub/python-package/issues
Author-email: lixelv <simonefremenko@gmail.com>
License-File: LICENSE
Classifier: License :: OSI Approved :: MIT License
Classifier: Operating System :: OS Independent
Classifier: Programming Language :: Python :: 3
Requires-Python: >=3.0
Requires-Dist: certifi
Requires-Dist: charset-normalizer
Requires-Dist: idna
Requires-Dist: mouseinfo
Requires-Dist: psutil
Requires-Dist: pyautogui
Requires-Dist: pygetwindow
Requires-Dist: pymsgbox
Requires-Dist: pynput
Requires-Dist: pyperclip
Requires-Dist: pyrect
Requires-Dist: pyscreeze
Requires-Dist: pytweening
Requires-Dist: requests
Requires-Dist: six
Requires-Dist: urllib3
Requires-Dist: wget
